autotest_tools/__init__.py
autotest_tools/action_word_tool/__init__.py
autotest_tools/action_word_tool/action_word.py
autotest_tools/api_tool/__init__.py
autotest_tools/api_tool/http_common.py
autotest_tools/api_tool/websocket_common.py
autotest_tools/assert_tool/__init__.py
autotest_tools/assert_tool/assertion.py
autotest_tools/assert_tool/verify.py
autotest_tools/browser_tool/__init__.py
autotest_tools/browser_tool/browser.py
autotest_tools/config_tool/__init__.py
autotest_tools/config_tool/conf_common.py
autotest_tools/csv_tool/__init__.py
autotest_tools/csv_tool/csv_common.py
autotest_tools/db_tool/__init__.py
autotest_tools/db_tool/sqlalchemy_tool.py
autotest_tools/element_tool/__init__.py
autotest_tools/element_tool/element_common.py
autotest_tools/json_tool/__init__.py
autotest_tools/json_tool/json_common.py
autotest_tools/log_tool/__init__.py
autotest_tools/log_tool/log_config.py
autotest_tools/log_tool/logtest.py
autotest_tools/ocr_tool/__init__.py
autotest_tools/ocr_tool/ocr_common.py
autotest_tools/re_tool/__init__.py
autotest_tools/re_tool/re_common.py
autotest_tools/time_tool/__init__.py
autotest_tools/time_tool/time_common.py
autotest_tools/tree_tool/__init__.py
autotest_tools/tree_tool/tree_common.py
autotest_tools/web_tool/__init__.py
autotest_tools/web_tool/alert.py
autotest_tools/web_tool/basepage.py
autotest_tools/web_tool/driver.py
autotest_tools/web_tool/ec.py
autotest_tools/web_tool/element.py
autotest_tools/web_tool/keyboard.py
autotest_tools/web_tool/mouse.py
autotest_tools/web_tool/select.py
autotest_tools/web_tool/ui.py
autotest_tools/web_tool/wait.py
autotest_tools/yaml_tool/__init__.py
autotest_tools/yaml_tool/yaml_common.py
autotest_tools-2.0.6.dist-info/LICENSE
autotest_tools-2.0.6.dist-info/METADATA
autotest_tools-2.0.6.dist-info/WHEEL
autotest_tools-2.0.6.dist-info/top_level.txt
autotest_tools-2.0.6.dist-info/RECORD
