Metadata-Version: 2.1
Name: autotest-tools
Version: 2.0.6
Summary: auto test tools
Home-page: https://gitee.com/isguxin/auto-test-tool
Author: Gu Xin
Author-email: g_xin@outlook.com
Classifier: Programming Language :: Python :: 3
Classifier: License :: OSI Approved :: MIT License
Classifier: Operating System :: OS Independent
Requires-Python: <3.11
License-File: LICENSE
Requires-Dist: selenium
Requires-Dist: sqlalchemy
Requires-Dist: colorlog
Requires-Dist: ddddocr
Requires-Dist: treelib
Requires-Dist: requests
Requires-Dist: pyyaml
Requires-Dist: websocket-client
